README.rst
setup.cfg
setup.py
alfredo/__init__.py
alfredo/cli.py
alfredo/descriptions.py
alfredo/http.py
alfredo/resource.py
alfredo/stream.py
alfredo/mixins/__init__.py
alfredo/mixins/lazy.py
alfredo/mixins/nested.py
alfredo_py.egg-info/PKG-INFO
alfredo_py.egg-info/SOURCES.txt
alfredo_py.egg-info/dependency_links.txt
alfredo_py.egg-info/entry_points.txt
alfredo_py.egg-info/requires.txt
alfredo_py.egg-info/top_level.txt